google_datacatalog_vertica_connector-0.9.0-py3.8-nspkg.pth
google/datacatalog_connectors/vertica/__init__.py
google/datacatalog_connectors/vertica/vertica2datacatalog_cli.py
google/datacatalog_connectors/vertica/config/__init__.py
google/datacatalog_connectors/vertica/config/metadata_definition.json
google/datacatalog_connectors/vertica/config/metadata_query.sql
google/datacatalog_connectors/vertica/scrape/__init__.py
google/datacatalog_connectors/vertica/scrape/metadata_scraper.py
google_datacatalog_vertica_connector-0.9.0.dist-info/METADATA
google_datacatalog_vertica_connector-0.9.0.dist-info/WHEEL
google_datacatalog_vertica_connector-0.9.0.dist-info/entry_points.txt
google_datacatalog_vertica_connector-0.9.0.dist-info/namespace_packages.txt
google_datacatalog_vertica_connector-0.9.0.dist-info/top_level.txt
google_datacatalog_vertica_connector-0.9.0.dist-info/RECORD
