Metadata-Version: 2.1
Name: google-datacatalog-vertica-connector
Version: 0.9.0
Summary: Package for ingesting Vertica metadata into Google Cloud Data Catalog
Home-page: UNKNOWN
Author: Google LLC
License: UNKNOWN
Platform: Posix; MacOS X; Windows
Classifier: Development Status :: 4 - Beta
Classifier: Natural Language :: English
Classifier: Programming Language :: Python
Classifier: Programming Language :: Python :: 3.6
Requires-Dist: vertica-python
Requires-Dist: google-datacatalog-rdbms-connector (>=0.12.0<0.13.0)
